djangoldp_babelfish/__init__.py
djangoldp_babelfish/admin.py
djangoldp_babelfish/apps.py
djangoldp_babelfish/djangoldp_urls.py
djangoldp_babelfish/models.py
djangoldp_babelfish/settings.py
djangoldp_babelfish/views.py
djangoldp_babelfish/management/__init__.py
djangoldp_babelfish/management/commands/__init__.py
djangoldp_babelfish/migrations/0001_initial.py
djangoldp_babelfish/migrations/0002_auto_20230720_1705.py
djangoldp_babelfish/migrations/__init__.py
djangoldp_babelfish-1.0.10.dist-info/METADATA
djangoldp_babelfish-1.0.10.dist-info/WHEEL
djangoldp_babelfish-1.0.10.dist-info/top_level.txt
djangoldp_babelfish-1.0.10.dist-info/RECORD
