Metadata-Version: 2.1
Name: djangoldp-babelfish
Version: 1.0.10
Summary: Djangoldp babelfish package which provides integration with the Babelfish API
Home-page: https://git.startinblox.com/applications/ontochain/packages/djangoldp-babelfish.git
Author: Startinblox
Author-email: benoit@startinblox.com
License: MIT
Requires-Dist: djangoldp (~=3.0)
Requires-Dist: djangoldp-account (~=3.0)
Provides-Extra: dev
Requires-Dist: factory-boy (>=2.11.0) ; extra == 'dev'
